{"province":"Dalarna County","districts":{"Abborrberget":{"neighborhoods":["Abborrberget"]},"Avesta":{"neighborhoods":["Avesta"]},"Bjursås":{"neighborhoods":["Bjursås"]},"Borlänge":{"neighborhoods":["Borlänge"]},"Brunna":{"neighborhoods":["Brunna"]},"Djurås":{"neighborhoods":["Djurås"]},"Enbacka":{"neighborhoods":["Enbacka"]},"Falun":{"neighborhoods":["Falun"]},"Gagnef":{"neighborhoods":["Gagnef"]},"Grycksbo":{"neighborhoods":["Grycksbo"]},"Grängesberg":{"neighborhoods":["Grängesberg"]},"Hedemora":{"neighborhoods":["Hedemora"]},"Horndal":{"neighborhoods":["Horndal"]},"Insjön":{"neighborhoods":["Insjön"]},"Järna":{"neighborhoods":["Järna"]},"Krylbo":{"neighborhoods":["Krylbo"]},"Leksand":{"neighborhoods":["Leksand"]},"Ludvika":{"neighborhoods":["Ludvika"]},"Långshyttan":{"neighborhoods":["Långshyttan"]},"Malung":{"neighborhoods":["Malung"]},"Mockfjärd":{"neighborhoods":["Mockfjärd"]},"Mora":{"neighborhoods":["Mora"]},"Nyhammar":{"neighborhoods":["Nyhammar"]},"Ornäs":{"neighborhoods":["Ornäs"]},"Orsa":{"neighborhoods":["Orsa"]},"Romme":{"neighborhoods":["Romme"]},"Rättvik":{"neighborhoods":["Rättvik"]},"Siljansnäs":{"neighborhoods":["Siljansnäs"]},"Smedby":{"neighborhoods":["Smedby"]},"Smedjebacken":{"neighborhoods":["Smedjebacken"]},"Svärdsjö":{"neighborhoods":["Svärdsjö"]},"Säter":{"neighborhoods":["Säter"]},"Vansbro":{"neighborhoods":["Vansbro"]},"Vikarbyn":{"neighborhoods":["Vikarbyn"]},"Älvdalen":{"neighborhoods":["Älvdalen"]}}}