{"province":"Riyadh","districts":{"Ad Dawādimī":{"neighborhoods":["Ad Dawādimī"]},"Ad Dilam":{"neighborhoods":["Ad Dilam"]},"Afif":{"neighborhoods":["Afif"]},"Ain AlBaraha":{"neighborhoods":["Ain AlBaraha"]},"Al Arţāwīyah":{"neighborhoods":["Al Arţāwīyah"]},"Al Bir":{"neighborhoods":["Al Bir"]},"Al Hair":{"neighborhoods":["Al Hair"]},"Al Jurayfah":{"neighborhoods":["Al Jurayfah"]},"Al Kharj":{"neighborhoods":["Al Kharj"]},"Ar Rayn":{"neighborhoods":["Ar Rayn"]},"As Salamiyah":{"neighborhoods":["As Salamiyah"]},"As Sulayyil":{"neighborhoods":["As Sulayyil"]},"Az Zulfī":{"neighborhoods":["Az Zulfī"]},"Dawadmi":{"neighborhoods":["Dawadmi"]},"Diriyah":{"neighborhoods":["Diriyah"]},"Harmah":{"neighborhoods":["Harmah"]},"Jalajil":{"neighborhoods":["Jalajil"]},"Layla":{"neighborhoods":["Layla"]},"Manfuha":{"neighborhoods":["Manfuha"]},"Marāt":{"neighborhoods":["Marāt"]},"Najan":{"neighborhoods":["Najan"]},"Najran":{"neighborhoods":["Najran"]},"Riyadh":{"neighborhoods":["Riyadh"]},"Sājir":{"neighborhoods":["Sājir"]},"Tumayr":{"neighborhoods":["Tumayr"]},"shokhaibٍ":{"neighborhoods":["shokhaibٍ"]}}}